e04go/app/__init__.py
e04go/E04master.py
e04go-0.0.1.3.dist-info/entry_points.txt
e04go-0.0.1.3.dist-info/LICENSE
e04go-0.0.1.3.dist-info/METADATA
e04go-0.0.1.3.dist-info/WHEEL
e04go-0.0.1.3.dist-info/RECORD
