Metadata-Version: 2.1
Name: e04go
Version: 0.0.1.3
Summary: 一個基於 FastAPI 的 MTV 架構生成器
Home-page: https://github.com/pisces860225/e04go
License: MIT
Author: QQ
Author-email: jeremy55688@icloud.com
Requires-Python: >=3.11,<4.0
Classifier: License :: OSI Approved :: MIT License
Classifier: Programming Language :: Python :: 3
Classifier: Programming Language :: Python :: 3.11
Requires-Dist: fastapi (>=0.115.0,<0.116.0)
Requires-Dist: jinja2 (>=3.1.4,<4.0.0)
Requires-Dist: pydantic (>=2.9.2,<3.0.0)
Requires-Dist: uvicorn (>=0.30.6,<0.31.0)
